CHANGELOG.txt
MANIFEST.in
README.md
setup.py
lokki/__init__.py
lokki.egg-info/PKG-INFO
lokki.egg-info/SOURCES.txt
lokki.egg-info/dependency_links.txt
lokki.egg-info/requires.txt
lokki.egg-info/top_level.txt
lokki/analyze/__init__.py
lokki/analyze/analysis_object.py
lokki/analyze/model_transform_analysis.py
lokki/api/__init__.py
lokki/api/factory.py
lokki/data_transform/__init__.py
lokki/data_transform/data_transformation_choice.py
lokki/data_transform/log.py
lokki/data_transform/void.py
lokki/data_transform/zscore.py
lokki/feature_transform/__init__.py
lokki/feature_transform/feature_transform_choice.py
lokki/feature_transform/feature_engineering/__init__.py
lokki/feature_transform/feature_engineering/factor.py
lokki/feature_transform/feature_engineering/ica.py
lokki/feature_transform/feature_engineering/nmf.py
lokki/feature_transform/feature_engineering/pca.py
lokki/feature_transform/feature_selection/__init__.py
lokki/feature_transform/feature_selection/chi_square.py
lokki/feature_transform/feature_selection/hfe.py
lokki/feature_transform/feature_selection/mutual.py
lokki/feature_transform/feature_selection/void.py
lokki/lib/__init__.py
lokki/lib/components.py
lokki/model/__init__.py
lokki/model/model_choice.py
lokki/model/sklearn/__init__.py
lokki/model/sklearn/adaboost.py
lokki/model/sklearn/decision_tree.py
lokki/model/sklearn/extra_tree.py
lokki/model/sklearn/gradient_boost.py
lokki/model/sklearn/lda.py
lokki/model/sklearn/logistic_regression.py
lokki/model/sklearn/qda.py
lokki/model/sklearn/random_forest.py
lokki/model/sklearn/ridge.py
lokki/model/sklearn/svm.py
lokki/selection/__init__.py
lokki/selection/model_selection.py
lokki/visualize/__init__.py
lokki/visualize/enrichment.py
lokki/visualize/performance_distribution.py